MANIFEST.in
setup.py
django_flexible_images.egg-info/PKG-INFO
django_flexible_images.egg-info/SOURCES.txt
django_flexible_images.egg-info/dependency_links.txt
django_flexible_images.egg-info/not-zip-safe
django_flexible_images.egg-info/requires.txt
django_flexible_images.egg-info/top_level.txt
flexible_images/__init__.py
flexible_images/models.py
flexible_images/util.py
flexible_images/views.py
flexible_images/migrations/0001_initial.py
flexible_images/migrations/__init__.py
flexible_images/static/.DS_Store
flexible_images/static/responsive-test-image-1.jpg
flexible_images/static/responsive-test-image-2.jpg
flexible_images/static/flexible-images/flexible-images.js
flexible_images/templates/flexible-images/flexible-image-test.html
flexible_images/templates/flexible-images/flexible-image.html
flexible_images/templatetags/__init__.py
flexible_images/templatetags/django_jinja_flexible_images.py
flexible_images/templatetags/flexible_images.py
flexible_images/tests/__init__.py
flexible_images/tests/base.py
flexible_images/tests/test_templatetags.py
flexible_images/tests/test_util.py