Metadata-Version: 1.1
Name: django-flexible-images
Version: 1.0.7
Summary: A responsive image solution for Django.
Home-page: https://github.com/lewiscollard/django-flexible-images
Author: Lewis Collard
Author-email: lewis.collard@onespacemedia.com
License: UNKNOWN
Platform: UNKNOWN
Classifier: Development Status :: 5 - Production/Stable
Classifier: Environment :: Web Environment
Classifier: Intended Audience :: Developers
Classifier: Framework :: Django
Classifier: Framework :: Django :: 1.8
Classifier: Natural Language :: English
Classifier: Programming Language :: Python :: 2.7
Classifier: License :: CC0 1.0 Universal (CC0 1.0) Public Domain Dedication
